drc_cmis/__init__.py
drc_cmis/admin.py
drc_cmis/apps.py
drc_cmis/client.py
drc_cmis/client_builder.py
drc_cmis/connections.py
drc_cmis/forms.py
drc_cmis/mixins.py
drc_cmis/models.py
drc_cmis/validators.py
drc_cmis/browser/__init__.py
drc_cmis/browser/client.py
drc_cmis/browser/drc_document.py
drc_cmis/browser/request.py
drc_cmis/browser/utils.py
drc_cmis/migrations/0001_initial_new.py
drc_cmis/migrations/0002_auto_20190523_1054.py
drc_cmis/migrations/0003_auto_20191029_1349.py
drc_cmis/migrations/0004_auto_20200616_0919.py
drc_cmis/migrations/0005_auto_20200723_1352.py
drc_cmis/migrations/0006_cmisconfig_binding.py
drc_cmis/migrations/0007_cmisconfig_time_zone.py
drc_cmis/migrations/0008_auto_20200806_1030.py
drc_cmis/migrations/0009_auto_20200810_0830.py
drc_cmis/migrations/0010_auto_20200811_1221.py
drc_cmis/migrations/0011_auto_20200813_1640.py
drc_cmis/migrations/0012_auto_20200821_1512.py
drc_cmis/migrations/0013_auto_20201216_1046.py
drc_cmis/migrations/0013_auto_20201224_1302.py
drc_cmis/migrations/0014_auto_20210106_1602.py
drc_cmis/migrations/0015_merge_20210204_1046.py
drc_cmis/migrations/0016_alter_cmisconfig_time_zone.py
drc_cmis/migrations/0017_cmisconfig_verzoek_folder_path.py
drc_cmis/migrations/0018_alter_cmisconfig_time_zone.py
drc_cmis/migrations/__init__.py
drc_cmis/static/drc_cmis/js/cmis_config.js
drc_cmis/templates/configuration_form.html
drc_cmis/utils/__init__.py
drc_cmis/utils/convert.py
drc_cmis/utils/exceptions.py
drc_cmis/utils/folder.py
drc_cmis/utils/mapper.py
drc_cmis/utils/query.py
drc_cmis/utils/utils.py
drc_cmis/webservice/__init__.py
drc_cmis/webservice/client.py
drc_cmis/webservice/data_models.py
drc_cmis/webservice/drc_document.py
drc_cmis/webservice/fetcher.py
drc_cmis/webservice/request.py
drc_cmis/webservice/utils.py
drc_cmis-1.9.1.dist-info/AUTHORS
drc_cmis-1.9.1.dist-info/LICENSE.md
drc_cmis-1.9.1.dist-info/METADATA
drc_cmis-1.9.1.dist-info/WHEEL
drc_cmis-1.9.1.dist-info/top_level.txt
drc_cmis-1.9.1.dist-info/RECORD
