Metadata-Version: 2.1
Name: drc-cmis
Version: 1.9.1
Summary: An adapter to manage Documenten API resources in a CMIS backend.
Home-page: https://github.com/open-zaak/cmis-adapter
Author: Maykin Media, Joeri Bekker, Jorik Kraaikamp, Sergei Maertens, Silvia Amabilino
Author-email: support@maykinmedia.nl
License: EUPL-1.2
Keywords: CMIS,Documenten API,VNG,Common Ground
Classifier: Development Status :: 5 - Production/Stable
Classifier: Framework :: Django
Classifier: Framework :: Django :: 3.2
Classifier: Framework :: Django :: 4.2
Classifier: Intended Audience :: Developers
Classifier: Operating System :: Unix
Classifier: Operating System :: MacOS
Classifier: Operating System :: Microsoft :: Windows
Classifier: Programming Language :: Python :: 3
Classifier: Programming Language :: Python :: 3 :: Only
Classifier: Programming Language :: Python :: 3.10
Classifier: Programming Language :: Python :: 3.11
Classifier: Programming Language :: Python :: Implementation :: CPython
Classifier: Topic :: Software Development :: Libraries :: Python Modules
License-File: LICENSE.md
License-File: AUTHORS
Requires-Dist: django >=3.2.0
Requires-Dist: cmislib-maykin >=0.7.2.dev0
Requires-Dist: django-solo
Requires-Dist: iso8601
Requires-Dist: commonground-api-common
Requires-Dist: python-decouple
Requires-Dist: furl
Provides-Extra: coverage
Requires-Dist: pytest-cov ; extra == 'coverage'
Provides-Extra: docs
Requires-Dist: sphinx ; extra == 'docs'
Requires-Dist: sphinx-rtd-theme ; extra == 'docs'
Provides-Extra: pep8
Requires-Dist: flake8 ; extra == 'pep8'
Provides-Extra: release
Requires-Dist: bumpversion ; extra == 'release'
Requires-Dist: twine ; extra == 'release'
Provides-Extra: tests
Requires-Dist: pytest ; extra == 'tests'
Requires-Dist: pytest-django ; extra == 'tests'
Requires-Dist: tox ; extra == 'tests'
Requires-Dist: isort ; extra == 'tests'
Requires-Dist: black ; extra == 'tests'
Requires-Dist: factory-boy >=3.0.0 ; extra == 'tests'
Requires-Dist: psycopg2 ; extra == 'tests'
Requires-Dist: responses ; extra == 'tests'
Requires-Dist: freezegun ; extra == 'tests'
Requires-Dist: requests-mock ; extra == 'tests'
